pyspinw/__init__.py
pyspinw/ctfs/SpinW_2021a.ctf
pyspinw/ctfs/SpinW_2021b.ctf
pyspinw/ctfs/SpinW_2022a.ctf
pyspinw/ctfs/SpinW_2022b.ctf
pyspinw/ctfs/SpinW_2023a.ctf
pyspinw/ctfs/SpinW_2023b.ctf
pyspinw/ctfs/SpinW_2024a.ctf
pyspinw/matlab_plotting.py
pyspinw/matlab_wrapped/__init__.py
pyspinw/matlab_wrapped/cif.py
pyspinw/matlab_wrapped/ndbase/__init__.py
pyspinw/matlab_wrapped/spinw.py
pyspinw/matlab_wrapped/sw_fitpowder.py
pyspinw/matlab_wrapped/swfunc/__init__.py
pyspinw/matlab_wrapped/swplot/__init__.py
pyspinw/matlab_wrapped/swpref.py
pyspinw/matlab_wrapped/swsym/__init__.py
pyspinw/matlab_wrapped/YAML.py
pyspinw/plotting.py
spinw-4.0.0.dist-info/METADATA
spinw-4.0.0.dist-info/WHEEL
spinw-4.0.0.dist-info/RECORD
