Metadata-Version: 2.1
Name: spinw
Version: 4.0.0
Summary: Python library for spin wave calculations
Home-page: https://spinw.org
License: BSD-3-Clause
Author: Sándor Tóth
Requires-Python: >=3.8,<=3.12
Classifier: Development Status :: 3 - Alpha
Classifier: Intended Audience :: Developers
Classifier: License :: OSI Approved :: BSD License
Classifier: Programming Language :: Python :: 3
Classifier: Programming Language :: Python :: 3.8
Classifier: Programming Language :: Python :: 3.9
Classifier: Programming Language :: Python :: 3.10
Classifier: Programming Language :: Python :: 3.11
Classifier: Programming Language :: Python :: 3.12
Classifier: Programming Language :: Python :: 3 :: Only
Classifier: Topic :: Scientific/Engineering :: Physics
Provides-Extra: test
Requires-Dist: codecov (>=2.1.11) ; extra == "test"
Requires-Dist: flake8 (>=5.0) ; extra == "test"
Requires-Dist: libpymcr (>=0.1.7)
Requires-Dist: numpy (>=1.21.4,<2.0.0)
Requires-Dist: pyqt5 (>=5.15,<5.16)
Requires-Dist: pytest (>=7.0.0) ; extra == "test"
Requires-Dist: pytest-cov (>=3,<5) ; extra == "test"
Requires-Dist: scipy (>=1.0.0)
Requires-Dist: tox (>=3.0) ; extra == "test"
Requires-Dist: tox-gh-actions (>=2.11,<4.0) ; extra == "test"
Requires-Dist: vispy (>=0.14.1)
